collective.cookiecuttr-2.0.1-py3.7-nspkg.pth
collective/cookiecuttr/__init__.py
collective/cookiecuttr/configure.zcml
collective/cookiecuttr/interfaces.py
collective/cookiecuttr/overrides.zcml
collective/cookiecuttr/testing.py
collective/cookiecuttr/upgrades.py
collective/cookiecuttr/browser/__init__.py
collective/cookiecuttr/browser/configure.zcml
collective/cookiecuttr/browser/controlpanel.py
collective/cookiecuttr/browser/viewlet.py
collective/cookiecuttr/locales/collective.cookiecuttr.pot
collective/cookiecuttr/locales/de/LC_MESSAGES/collective.cookiecuttr.po
collective/cookiecuttr/locales/en/LC_MESSAGES/collective.cookiecuttr.po
collective/cookiecuttr/locales/nl/LC_MESSAGES/collective.cookiecuttr.po
collective/cookiecuttr/profiles/default/browserlayer.xml
collective/cookiecuttr/profiles/default/controlpanel.xml
collective/cookiecuttr/profiles/default/metadata.xml
collective/cookiecuttr/profiles/default/registry.xml
collective/cookiecuttr/profiles/uninstall/browserlayer.xml
collective/cookiecuttr/profiles/uninstall/controlpanel.xml
collective/cookiecuttr/profiles/uninstall/registry.xml
collective/cookiecuttr/static/cookiecuttr.css
collective/cookiecuttr/static/cookiecuttr.js
collective/cookiecuttr/static/cookiecuttr.min.css
collective/cookiecuttr/static/cookiecuttr.min.js
collective/cookiecuttr/static/cookiecuttr.png
collective/cookiecuttr/static/jquery.cookie.js
collective/cookiecuttr/tests/__init__.py
collective/cookiecuttr/tests/test_controlpanel.py
collective/cookiecuttr/tests/test_install.py
collective/cookiecuttr/tests/test_viewlet.py
collective.cookiecuttr-2.0.1.dist-info/METADATA
collective.cookiecuttr-2.0.1.dist-info/WHEEL
collective.cookiecuttr-2.0.1.dist-info/entry_points.txt
collective.cookiecuttr-2.0.1.dist-info/namespace_packages.txt
collective.cookiecuttr-2.0.1.dist-info/top_level.txt
collective.cookiecuttr-2.0.1.dist-info/RECORD
