Metadata-Version: 2.1
Name: collective.cookiecuttr
Version: 2.0.1
Summary: Integration package for cookiecuttr, european guidelines
Home-page: https://github.com/collective/collective.cookiecuttr
Author: Franklin Kingma
Author-email: franklin@fourdigits.nl
License: GPL
Keywords: cookies
Platform: UNKNOWN
Classifier: Development Status :: 5 - Production/Stable
Classifier: Environment :: Web Environment
Classifier: Framework :: Plone
Classifier: Framework :: Plone :: 5.2
Classifier: Framework :: Plone :: 6.0
Classifier: Programming Language :: Python
Classifier: Programming Language :: Python :: 3.7
Classifier: Programming Language :: Python :: 3.8
Classifier: Programming Language :: Python :: 3.9
Classifier: Programming Language :: Python :: 3.10
Classifier: Programming Language :: Python :: 3.11
Classifier: Operating System :: OS Independent
Classifier: License :: OSI Approved :: GNU General Public License v2 (GPLv2)
Requires-Python: >=3.6
Requires-Dist: setuptools
Requires-Dist: plone.app.registry
Requires-Dist: plone.app.layout
Requires-Dist: plone.browserlayer
Requires-Dist: collective.z3cform.datagridfield
Provides-Extra: test
Requires-Dist: plone.app.testing ; extra == 'test'
Requires-Dist: zope.testrunner ; extra == 'test'
